quine/runtimes/uart/__init__.py
quine_runtime_uart-0.0.0.dist-info/COPYING.md
quine_runtime_uart-0.0.0.dist-info/METADATA
quine_runtime_uart-0.0.0.dist-info/WHEEL
quine_runtime_uart-0.0.0.dist-info/RECORD
