Metadata-Version: 2.3
Name: quine-runtime-uart
Version: 0.0.0
Summary: Quine runtime environment for UART
License: AGPL-3.0-or-later
Author: Hendrik M Halkow
Author-email: hendrik@halkow.com
Requires-Python: >=3.13,<4.0
Classifier: Development Status :: 3 - Alpha
Classifier: Environment :: Console
Classifier: Intended Audience :: Developers
Classifier: Intended Audience :: Education
Classifier: Intended Audience :: Information Technology
Classifier: Intended Audience :: Science/Research
Classifier: License :: OSI Approved :: GNU Affero General Public License v3
Classifier: Natural Language :: English
Classifier: Operating System :: OS Independent
Classifier: Programming Language :: Python
Classifier: Programming Language :: Python :: 3
Classifier: Programming Language :: Python :: 3.13
Classifier: Topic :: Software Development :: Assemblers
Classifier: Topic :: Software Development :: Build Tools
Classifier: Topic :: Software Development :: Compilers
Classifier: Topic :: Software Development :: Testing
Classifier: Topic :: System :: Boot :: Init
Classifier: Topic :: System :: Operating System
Classifier: Topic :: Utilities
Project-URL: Documentation, https://docs.quine.build
Project-URL: Homepage, https://quine.build
Project-URL: Repository, https://github.com/quine-build/quine-runtime-uart
